attention_smithy/__init__.py
attention_smithy/test_functions.py
attention_smithy/utils.py
attention_smithy/attention/BigBirdAttentionMethod.py
attention_smithy/attention/HyenaMethod.py
attention_smithy/attention/StandardAttentionMethod.py
attention_smithy/attention/__init__.py
attention_smithy/attention/tests/__init__.py
attention_smithy/attention/tests/test_BigBirdAttentionMethod.py
attention_smithy/attention/tests/test_StandardAttentionMethod.py
attention_smithy/components/Decoder.py
attention_smithy/components/DecoderLayer.py
attention_smithy/components/Encoder.py
attention_smithy/components/EncoderLayer.py
attention_smithy/components/FeedForwardNetwork.py
attention_smithy/components/MultiheadAttention.py
attention_smithy/components/SublayerUnit.py
attention_smithy/components/__init__.py
attention_smithy/components/tests/__init__.py
attention_smithy/components/tests/test_Decoder.py
attention_smithy/components/tests/test_DecoderLayer.py
attention_smithy/components/tests/test_Encoder.py
attention_smithy/components/tests/test_EncoderLayer.py
attention_smithy/components/tests/test_FeedForwardNetwork.py
attention_smithy/components/tests/test_MultiheadAttention.py
attention_smithy/components/tests/test_SublayerUnit.py
attention_smithy/generators/BeamGenerator.py
attention_smithy/generators/GeneratorContext.py
attention_smithy/generators/GeneratorModuleAbstractClass.py
attention_smithy/generators/GeneratorStrategy.py
attention_smithy/generators/GreedyGenerator.py
attention_smithy/generators/__init__.py
attention_smithy/generators/tests/__init__.py
attention_smithy/generators/tests/test_BeamGenerator.py
attention_smithy/generators/tests/test_GeneratorContext.py
attention_smithy/generators/tests/test_GreedyGenerator.py
attention_smithy/numeric_embeddings/ALiBiEmbedding.py
attention_smithy/numeric_embeddings/LearnedEmbedding.py
attention_smithy/numeric_embeddings/NumericEmbeddingManager.py
attention_smithy/numeric_embeddings/RotaryEmbedding.py
attention_smithyr-1.0.0.dist-info/LICENSE
attention_smithyr-1.0.0.dist-info/METADATA
attention_smithyr-1.0.0.dist-info/WHEEL
attention_smithyr-1.0.0.dist-info/top_level.txt
attention_smithyr-1.0.0.dist-info/RECORD
